smol_sae/__init__.py
smol_sae/anthropic.py
smol_sae/base.py
smol_sae/gated.py
smol_sae/main.py
smol_sae/rainbow.py
smol_sae/utils.py
smol_sae/vanilla.py
smol_sae-0.1.0.dist-info/METADATA
smol_sae-0.1.0.dist-info/WHEEL
smol_sae-0.1.0.dist-info/RECORD
