Metadata-Version: 2.3
Name: smol-sae
Version: 0.1.0
Summary: Minimal implementation of SAEs
Author-email: Daniel Tan <dtch1997@users.noreply.github.com>, Daniel CH Tan <dtch1997@users.noreply.github.com>
License: MIT
Requires-Python: >=3.10
Requires-Dist: einops>=0.8.0
Requires-Dist: torch>=2.3.0
Requires-Dist: tqdm>=4.66.4
Requires-Dist: transformer-lens>=1.17.0
Requires-Dist: wandb>=0.17.0
Provides-Extra: test
Requires-Dist: pre-commit>=3.7.0; extra == 'test'
Requires-Dist: pyright>=1.1.361; extra == 'test'
Requires-Dist: pytest>=8.2.0; extra == 'test'
Requires-Dist: ruff>=0.4.3; extra == 'test'
